landuse_mcp/__init__.py
landuse_mcp/__main__.py
landuse_mcp/_version.py
landuse_mcp/main.py
landuse_mcp-0.1.9.dist-info/METADATA
landuse_mcp-0.1.9.dist-info/WHEEL
landuse_mcp-0.1.9.dist-info/entry_points.txt
landuse_mcp-0.1.9.dist-info/licenses/LICENSE
landuse_mcp-0.1.9.dist-info/RECORD
